finicapi/__init__.py
finicapi/cli.py
finicapi/finic.py
finicapi-0.1.30.dist-info/METADATA
finicapi-0.1.30.dist-info/WHEEL
finicapi-0.1.30.dist-info/entry_points.txt
finicapi-0.1.30.dist-info/RECORD
